CHANGES.txt
LICENSE.rst
README.rst
setup.py
js/__init__.py
js.ngupload.egg-info/PKG-INFO
js.ngupload.egg-info/SOURCES.txt
js.ngupload.egg-info/dependency_links.txt
js.ngupload.egg-info/entry_points.txt
js.ngupload.egg-info/namespace_packages.txt
js.ngupload.egg-info/not-zip-safe
js.ngupload.egg-info/requires.txt
js.ngupload.egg-info/top_level.txt
js/ngupload/__init__.py
js/ngupload/test_ngupload.txt
js/ngupload/resources/upload.js
js/ngupload/resources/upload.min.js