Metadata-Version: 1.0
Name: js.ngupload
Version: 0.3.0
Summary: Fanstatic packaging of ngUpload
Home-page: https://github.com/disko/js.ngupload
Author: Andreas Kaiser
Author-email: disko@binary-punks.com
License: BSD
Keywords: Fanstatic ngUpload
Platform: UNKNOWN
Classifier: Development Status :: 5 - Production/Stable
Classifier: Intended Audience :: Developers
Classifier: License :: OSI Approved :: BSD License
Classifier: Programming Language :: Python :: 2.6
Classifier: Programming Language :: Python :: 2.7
Classifier: Programming Language :: Python :: 3
Classifier: Programming Language :: Python :: 3.2
Classifier: Programming Language :: Python :: 3.3
Classifier: Topic :: Internet :: WWW/HTTP :: Dynamic Content
Classifier: Topic :: Internet :: WWW/HTTP :: WSGI :: Middleware
